spacy_aligner/__init__.py
spacy_aligner/pipeline.py
spacy_aligner-0.0.1.dist-info/METADATA
spacy_aligner-0.0.1.dist-info/WHEEL
spacy_aligner-0.0.1.dist-info/top_level.txt
spacy_aligner-0.0.1.dist-info/RECORD
