Metadata-Version: 2.1
Name: spacy-aligner
Version: 0.0.1
Summary: A spaCy component for connecting entities and building relational graphs in text.
Home-page: https://github.com/wjbmattingly/spacy_aligner
Author: William J.B. Mattingly
Classifier: Development Status :: 3 - Alpha
Classifier: Intended Audience :: Developers
Classifier: Topic :: Software Development :: Libraries :: Python Modules
Classifier: License :: OSI Approved :: MIT License
Classifier: Programming Language :: Python :: 3
Classifier: Programming Language :: Python :: 3.7
Classifier: Programming Language :: Python :: 3.8
Classifier: Programming Language :: Python :: 3.9
Classifier: Programming Language :: Python :: 3.10
Classifier: Programming Language :: Python :: 3.11
Requires-Python: >=3.7
Requires-Dist: spacy
Requires-Dist: networkx
